lino_weleup/__init__.py
lino_weleup/settings.py
lino_weleup/lib/__init__.py
lino_weleup/lib/pcsw/__init__.py
lino_weleup/lib/pcsw/models.py
lino_weleup/lib/pcsw/fixtures/__init__.py
lino_weleup/lib/pcsw/fixtures/demo2.py
lino_weleup/lib/pcsw/fixtures/std.py
lino_weleup/locale/django.pot
lino_weleup/locale/de/LC_MESSAGES/django.mo
lino_weleup/locale/de/LC_MESSAGES/django.po
lino_weleup/locale/fr/LC_MESSAGES/django.mo
lino_weleup/locale/fr/LC_MESSAGES/django.po
lino_weleup/locale/nl/LC_MESSAGES/django.mo
lino_weleup/locale/nl/LC_MESSAGES/django.po
lino_weleup-25.4.0.dist-info/METADATA
lino_weleup-25.4.0.dist-info/WHEEL
lino_weleup-25.4.0.dist-info/licenses/COPYING
lino_weleup-25.4.0.dist-info/RECORD
